Metadata-Version: 1.0
Name: validate-yml
Version: 1.0.0
Summary: validate yml syntax
Home-page: UNKNOWN
Author: jimmy
Author-email: zjm901026@163.com
License: GPL
Keywords: validate,yml
Platform: Independant
